swritructure/__init__.py
swritructure/swritructure.py
swritructure/test_execute.py
swritructure-2.1.0.dist-info/METADATA
swritructure-2.1.0.dist-info/WHEEL
swritructure-2.1.0.dist-info/top_level.txt
swritructure-2.1.0.dist-info/RECORD
