Metadata-Version: 2.1
Name: swritructure
Version: 2.1.0
Summary: Please use it when you want to extract only the common part of two csv.
Home-page: https://github.com/taotaotao3/swritructure
Author: Takao Morita
Author-email: tmolita077@gmail.com
License: MIT
Keywords: structure,program,analysis,folder,directory
Platform: UNKNOWN
Classifier: Development Status :: 5 - Production/Stable
Classifier: License :: OSI Approved :: BSD License
Classifier: Programming Language :: Python
Classifier: Programming Language :: Python :: 3
Classifier: Programming Language :: Python :: 3.4
Classifier: Programming Language :: Python :: 3.5
Classifier: Programming Language :: Python :: 3.6
Classifier: Programming Language :: Python :: 3.7
Classifier: Programming Language :: Python :: 3.8
Classifier: Topic :: Database
Classifier: Topic :: Software Development :: Libraries :: Python Modules
Requires-Dist: setuptools (==52.0.0.post20210125)
